odoo/addons/sale_readonly_security/README.rst
odoo/addons/sale_readonly_security/__init__.py
odoo/addons/sale_readonly_security/__manifest__.py
odoo/addons/sale_readonly_security/i18n/es.po
odoo/addons/sale_readonly_security/i18n/it.po
odoo/addons/sale_readonly_security/i18n/sale_readonly_security.pot
odoo/addons/sale_readonly_security/models/__init__.py
odoo/addons/sale_readonly_security/models/sale_order.py
odoo/addons/sale_readonly_security/readme/CONTEXT.md
odoo/addons/sale_readonly_security/readme/CONTRIBUTORS.md
odoo/addons/sale_readonly_security/readme/DESCRIPTION.md
odoo/addons/sale_readonly_security/readme/USAGE.md
odoo/addons/sale_readonly_security/security/sale_readonly_security_security.xml
odoo/addons/sale_readonly_security/static/description/icon.png
odoo/addons/sale_readonly_security/static/description/index.html
odoo/addons/sale_readonly_security/tests/__init__.py
odoo/addons/sale_readonly_security/tests/test_sale_readonly_security.py
odoo_addon_sale_readonly_security-18.0.1.0.0.2.dist-info/METADATA
odoo_addon_sale_readonly_security-18.0.1.0.0.2.dist-info/WHEEL
odoo_addon_sale_readonly_security-18.0.1.0.0.2.dist-info/top_level.txt
odoo_addon_sale_readonly_security-18.0.1.0.0.2.dist-info/RECORD
